Delay/delay.v
module D (out, a, b, c);
    input a, b, c;
    output out;

    wire w1;

    and #5 a1 (w1, a, b);
    or #4 o1 (out, w1, c);
endmodule

Delay/tb_delay.v
module stimulus;

    reg a, b, c;
    wire out;

    D d1 (out, a, b, c);

    initial begin
        $dumpfile("delay.vcd");
        $dumpvars(0, stimulus);
        a = 0; b = 0; c = 0;
        #10 a = 1;
        #10 b = 1;
        #10 c = 1;
        #10 a = 0;
        #10 b = 0;
        #10 c = 0;
        #10 $finish;
    end
endmodule

Delay/delay.vcd
$date
	Sun Apr 13 22:38:06 2025
$end
$version
	Icarus Verilog
$end
$timescale
	1s
$end
$scope module stimulus $end
$var wire 1 ! out $end
$var reg 1 " a $end
$var reg 1 # b $end
$var reg 1 $ c $end
$scope module d1 $end
$var wire 1 " a $end
$var wire 1 # b $end
$var wire 1 $ c $end
$var wire 1 ! out $end
$var wire 1 % w1 $end
$upscope $end
$upscope $end
$enddefinitions $end
$comment Show the parameter values. $end
$dumpall
$end
#0
$dumpvars
x%
0$
0#
0"
x!
$end
#5
0%
#9
0!
#10
1"
#20
1#
#25
1%
#29
1!
#30
1$
#40
0"
#45
0%
#50
0#
#60
0$
#64
0!
