4-to-1_MUX/mux.v
module mux (out, i0, i1, i2, i3, s0, s1);
    output out;
    input i0, i1, i2, i3;
    input s0, s1;

    wire s0n, s1n;
    wire w0, w1, w2, w3;

    or o1 (out, w0, w1, w2, w3);

    and a0 (w0, i0, s0n, s1n);
    and a1 (w1, i1, s0, s1n);
    and a2 (w2, i2, s0n, s1);
    and a3 (w3, i3, s0, s1);

    not n0 (s0n, s0);
    not n1 (s1n, s1);

endmodule

4-to-1_MUX/tb_mux.v
module stimulus;
    reg i0, i1, i2, i3, s0, s1;
    wire out;

    mux m1 (out, i0, i1, i2, i3, s0, s1);

    initial begin
        $dumpfile("mux.vcd");
        $dumpvars(0, stimulus);
        $monitor($time, " i0=%b i1=%b i2=%b i3=%b s0=%b s1=%b out=%b", i0, i1, i2, i3, s0, s1, out);
        i0 = 0; i1 = 0; i2 = 0; i3 = 0; s0 = 0; s1 = 0;
        #5 i0 = 1; i1 = 0; i2 = 0; i3 = 0; s0 = 0; s1 = 0;
        #5 i0 = 0; i1 = 1; i2 = 0; i3 = 0; s0 = 0; s1 = 1;
        #5 i0 = 0; i1 = 0; i2 = 1; i3 = 0; s0 = 1; s1 = 0;
        #5 i0 = 0; i1 = 0; i2 = 0; i3 = 1; s0 = 1; s1 = 1;
        #5 i0 = 1; i1 = 1; i2 = 0; i3 = 0; s0 = 0; s1 = 0;
        #5 i0 = 0; i1 = 1; i2 = 1; i3 = 0; s0 = 0; s1 = 1;
        #5 i0 = 0; i1 = 0; i2 = 1; i3 = 1; s0 = 1; s1 = 0;
        #5 $finish;
    end

endmodule

4-to-1_MUX/mux.vcd
$date
	Sun Apr 13 17:08:32 2025
$end
$version
	Icarus Verilog
$end
$timescale
	1s
$end
$scope module stimulus $end
$var wire 1 ! out $end
$var reg 1 " i0 $end
$var reg 1 # i1 $end
$var reg 1 $ i2 $end
$var reg 1 % i3 $end
$var reg 1 & s0 $end
$var reg 1 ' s1 $end
$scope module m1 $end
$var wire 1 " i0 $end
$var wire 1 # i1 $end
$var wire 1 $ i2 $end
$var wire 1 % i3 $end
$var wire 1 ! out $end
$var wire 1 & s0 $end
$var wire 1 ( s0n $end
$var wire 1 ' s1 $end
$var wire 1 ) s1n $end
$var wire 1 * w0 $end
$var wire 1 + w1 $end
$var wire 1 , w2 $end
$var wire 1 - w3 $end
$upscope $end
$upscope $end
$enddefinitions $end
$comment Show the parameter values. $end
$dumpall
$end
#0
$dumpvars
0-
0,
0+
0*
1)
1(
0'
0&
0%
0$
0#
0"
0!
$end
#5
1!
1*
1"
#10
0!
0)
0*
1'
1#
0"
#15
1)
0(
0'
1&
1$
0#
#20
1!
0)
1-
1'
1%
0$
#25
1*
1!
1)
1(
0-
0'
0&
0%
1#
1"
#30
0)
1,
0*
1'
1$
0"
#35
0!
0,
1)
0(
0'
1&
1%
0#
