Ripple_counter/RC.v
module RC (q, clk, rst);
    output [3:0] q;
    input clk, rst;

    T_FF tff0 (q[0], clk, rst);
    T_FF tff1 (q[1], q[0], rst);
    T_FF tff2 (q[2], q[1], rst);
    T_FF tff3 (q[3], q[2], rst);
endmodule

module T_FF (q, clk, rst);
    output q;
    input clk, rst;

    wire d, q_;
    
    not n1 (d, q);

    D_FF dff0 (q, q_, d, clk, rst);
endmodule

module D_FF (q, q_, d, clk, rst);
    output q, q_;
    input d, clk, rst;

    wire clk_, rst_, s, s_, r, r_;

    not n1 (rst_, rst);
    not n2 (clk_, clk);
    
    nand na1 (s_, r_, s);
    nand na2 (s, s_, rst_, clk_);
    nand na3 (r, s, r_, clk_);
    nand na4 (r_, r, rst_, d);

    nand na5 (q, s, q_);
    nand na6 (q_, q, r, rst_);
endmodule

Ripple_counter/tb_RC.v
module stimulus;
    reg clk, rst;
    wire [3:0] q;

    RC rc (q, clk, rst);

    initial begin
        clk = 1'b0;
        forever #10 clk = ~clk;
    end

    initial begin
        $dumpfile("RC.vcd");
        $dumpvars(0, stimulus);
        rst = 1'b1;
        #34 rst = 1'b0;
        #200 rst = 1'b1;
        #50 rst = 1'b0;
        clk = 1'b0;
    end

    initial
        #400 $finish;
endmodule

Ripple_counter/RC.vcd
$date
	Mon Apr 14 00:13:53 2025
$end
$version
	Icarus Verilog
$end
$timescale
	1s
$end
$scope module stimulus $end
$var wire 4 ! q [3:0] $end
$var reg 1 " clk $end
$var reg 1 # rst $end
$scope module rc $end
$var wire 1 " clk $end
$var wire 1 # rst $end
$var wire 4 $ q [3:0] $end
$scope module tff0 $end
$var wire 1 " clk $end
$var wire 1 % d $end
$var wire 1 # rst $end
$var wire 1 & q_ $end
$var wire 1 ' q $end
$scope module dff0 $end
$var wire 1 " clk $end
$var wire 1 ( clk_ $end
$var wire 1 % d $end
$var wire 1 ' q $end
$var wire 1 & q_ $end
$var wire 1 ) r $end
$var wire 1 * r_ $end
$var wire 1 # rst $end
$var wire 1 + rst_ $end
$var wire 1 , s $end
$var wire 1 - s_ $end
$upscope $end
$upscope $end
$scope module tff1 $end
$var wire 1 . clk $end
$var wire 1 / d $end
$var wire 1 # rst $end
$var wire 1 0 q_ $end
$var wire 1 1 q $end
$scope module dff0 $end
$var wire 1 . clk $end
$var wire 1 2 clk_ $end
$var wire 1 / d $end
$var wire 1 1 q $end
$var wire 1 0 q_ $end
$var wire 1 3 r $end
$var wire 1 4 r_ $end
$var wire 1 # rst $end
$var wire 1 5 rst_ $end
$var wire 1 6 s $end
$var wire 1 7 s_ $end
$upscope $end
$upscope $end
$scope module tff2 $end
$var wire 1 8 clk $end
$var wire 1 9 d $end
$var wire 1 # rst $end
$var wire 1 : q_ $end
$var wire 1 ; q $end
$scope module dff0 $end
$var wire 1 8 clk $end
$var wire 1 < clk_ $end
$var wire 1 9 d $end
$var wire 1 ; q $end
$var wire 1 : q_ $end
$var wire 1 = r $end
$var wire 1 > r_ $end
$var wire 1 # rst $end
$var wire 1 ? rst_ $end
$var wire 1 @ s $end
$var wire 1 A s_ $end
$upscope $end
$upscope $end
$scope module tff3 $end
$var wire 1 B clk $end
$var wire 1 C d $end
$var wire 1 # rst $end
$var wire 1 D q_ $end
$var wire 1 E q $end
$scope module dff0 $end
$var wire 1 B clk $end
$var wire 1 F clk_ $end
$var wire 1 C d $end
$var wire 1 E q $end
$var wire 1 D q_ $end
$var wire 1 G r $end
$var wire 1 H r_ $end
$var wire 1 # rst $end
$var wire 1 I rst_ $end
$var wire 1 J s $end
$var wire 1 K s_ $end
$upscope $end
$upscope $end
$upscope $end
$upscope $end
$enddefinitions $end
$comment Show the parameter values. $end
$dumpall
$end
#0
$dumpvars
0K
1J
0I
1H
0G
1F
0E
1D
1C
0B
0A
1@
0?
1>
0=
1<
0;
1:
19
08
07
16
05
14
03
12
01
10
1/
0.
0-
1,
0+
1*
0)
1(
0'
1&
1%
b0 $
1#
0"
b0 !
$end
#10
1)
0(
1"
#20
0)
1(
0"
#30
1)
0(
1"
#34
1-
0*
1+
15
1?
1I
0#
#40
17
04
13
1*
02
0&
0%
1.
b1 !
b1 $
1'
0,
1(
0"
#50
0-
1,
0(
1"
#60
1A
0>
1=
14
0<
00
0/
18
11
06
12
1%
0.
b10 !
b10 $
0'
1&
0)
1(
0"
#70
1-
0*
1)
0(
1"
#80
07
16
1*
02
0&
0%
1.
b11 !
b11 $
1'
0,
1(
0"
#90
0-
1,
0(
1"
#100
1K
0H
1G
1>
0F
0:
09
1B
1;
0@
1<
1/
08
01
10
03
12
1%
0.
b100 !
b100 $
0'
1&
0)
1(
0"
#110
1-
0*
1)
0(
1"
#120
17
04
13
1*
02
0&
0%
1.
b101 !
b101 $
1'
0,
1(
0"
#130
0-
1,
0(
1"
#140
0A
1@
14
0<
00
0/
18
11
06
12
1%
0.
b110 !
b110 $
0'
1&
0)
1(
0"
#150
1-
0*
1)
0(
1"
#160
07
16
1*
02
0&
0%
1.
b111 !
b111 $
1'
0,
1(
0"
#170
0-
1,
0(
1"
#180
1H
0D
0C
1E
0J
1F
19
0B
0;
1:
0=
1<
1/
08
01
10
03
12
1%
0.
b1000 !
b1000 $
0'
1&
0)
1(
0"
#190
1-
0*
1)
0(
1"
#200
17
04
13
1*
02
0&
0%
1.
b1001 !
b1001 $
1'
0,
1(
0"
#210
0-
1,
0(
1"
#220
1A
0>
1=
14
0<
00
0/
18
11
06
12
1%
0.
b1010 !
b1010 $
0'
1&
0)
1(
0"
#230
1-
0*
1)
0(
1"
#234
0=
1<
1/
08
1C
0-
03
07
01
0A
0G
0K
b0 !
b0 $
0E
1*
16
10
1>
1J
1D
0+
05
0?
0I
1#
#240
0)
1(
0"
#250
1)
0(
1"
#260
0)
1(
0"
#270
1)
0(
1"
#280
0)
1(
0"
#284
1+
15
1?
1I
0#
#290
1-
0*
1)
0(
1"
#300
17
04
13
1*
02
0&
0%
1.
b1 !
b1 $
1'
0,
1(
0"
#310
0-
1,
0(
1"
#320
1A
0>
1=
14
0<
00
0/
18
11
06
12
1%
0.
b10 !
b10 $
0'
1&
0)
1(
0"
#330
1-
0*
1)
0(
1"
#340
07
16
1*
02
0&
0%
1.
b11 !
b11 $
1'
0,
1(
0"
#350
0-
1,
0(
1"
#360
1K
0H
1G
1>
0F
0:
09
1B
1;
0@
1<
1/
08
01
10
03
12
1%
0.
b100 !
b100 $
0'
1&
0)
1(
0"
#370
1-
0*
1)
0(
1"
#380
17
04
13
1*
02
0&
0%
1.
b101 !
b101 $
1'
0,
1(
0"
#390
0-
1,
0(
1"
#400
0A
1@
14
0<
00
0/
18
11
06
12
1%
0.
b110 !
b110 $
0'
1&
0)
1(
0"
