traffic_signal_controller/traffic_FSM.v
module traffic_signal (hwy, cntry, x, clk, rst);
    output reg [1:0] hwy, cntry;
    input clk, rst;
    input x;

    parameter RED = 2'b00;
    parameter YELLOW = 2'b01;
    parameter GREEN = 2'b10;

    parameter S0 = 3'b000; // hwy green, cntry red
    parameter S1 = 3'b001; // hwy yellow, cntry red
    parameter S2 = 3'b010; // hwy red, cntry red
    parameter S3 = 3'b011; // hwy red, cntry green
    parameter S4 = 3'b100; // hwy red, cntry yellow

    reg [2:0] state, next_state;
    always @(posedge clk or posedge rst) begin
        if (rst)
            state <= S0;
        else
            state <= next_state;
    end

    always @(*) begin
        hwy = GREEN;
        cntry = RED;
        case (state)
            S0: ;
            S1: hwy = YELLOW;
            S2: hwy = RED;
            S3: begin
                hwy = RED;
                cntry = GREEN;
            end
            S4: begin
                hwy = RED;
                cntry = YELLOW;
            end
        endcase
    end

    always @(state or x) begin
        case (state)
            S0: next_state = (x) ? S1 : S0;
            S1: next_state = S2;
            S2: next_state = (x) ? S3 : S2;
            S3: next_state = S4;
            S4: next_state = S0;
            default: next_state = S0;
        endcase
    end
endmodule

traffic_signal_controller/tb_traffic_FSM.v
`timescale 1ns/1ps

module traffic_signal_tb;

    // 輸入/輸出宣告
    reg clk, rst, x;
    wire [1:0] hwy, cntry;

    // 實例化你的模組
    traffic_signal uut (
        .hwy(hwy),
        .cntry(cntry),
        .x(x),
        .clk(clk),
        .rst(rst)
    );

    // 時脈產生器
    initial begin
        clk = 0;
        forever #5 clk = ~clk; // 10ns 一個週期
    end

    // 測試流程
    initial begin
        // 初始化
        rst = 1;
        x = 0;

        #12; // 等待一個不是整數倍的時脈週期（測試 async reset）
        rst = 0;

        // 一段時間內都沒有鄉村車來（x=0）
        #50;

        // 有車來（x=1）
        x = 1;
        #100;

        // 車走了（x=0）
        x = 0;
        #100;

        // 再次有車來
        x = 1;
        #80;

        // 結束模擬
        $finish;
    end

    // 顯示訊號變化
    initial begin
        $dumpfile("traffic_signal_tb.vcd");
        $dumpvars(0, traffic_signal_tb);
        $monitor("Time: %0t | x=%b | hwy=%b | cntry=%b | state=%b", $time, x, hwy, cntry, uut.state);
    end

endmodule

traffic_signal_controller/traffic_signal_tb.vcd
$date
	Mon Apr 14 19:44:34 2025
$end
$version
	Icarus Verilog
$end
$timescale
	1ps
$end
$scope module traffic_signal_tb $end
$var wire 2 ! hwy [1:0] $end
$var wire 2 " cntry [1:0] $end
$var reg 1 # clk $end
$var reg 1 $ rst $end
$var reg 1 % x $end
$scope module uut $end
$var wire 1 # clk $end
$var wire 1 $ rst $end
$var wire 1 % x $end
$var parameter 2 & GREEN $end
$var parameter 2 ' RED $end
$var parameter 3 ( S0 $end
$var parameter 3 ) S1 $end
$var parameter 3 * S2 $end
$var parameter 3 + S3 $end
$var parameter 3 , S4 $end
$var parameter 2 - YELLOW $end
$var reg 2 . cntry [1:0] $end
$var reg 2 / hwy [1:0] $end
$var reg 3 0 next_state [2:0] $end
$var reg 3 1 state [2:0] $end
$upscope $end
$upscope $end
$enddefinitions $end
$comment Show the parameter values. $end
$dumpall
b1 -
b100 ,
b11 +
b10 *
b1 )
b0 (
b0 '
b10 &
$end
#0
$dumpvars
b0 1
b0 0
b10 /
b0 .
0%
1$
0#
b0 "
b10 !
$end
#5000
1#
#10000
0#
#12000
0$
#15000
1#
#20000
0#
#25000
1#
#30000
0#
#35000
1#
#40000
0#
#45000
1#
#50000
0#
#55000
1#
#60000
0#
#62000
b1 0
1%
#65000
b10 0
b1 !
b1 /
b1 1
1#
#70000
0#
#75000
b11 0
b0 !
b0 /
b10 1
1#
#80000
0#
#85000
b100 0
b10 "
b10 .
b0 !
b0 /
b11 1
1#
#90000
0#
#95000
b0 0
b1 "
b1 .
b0 !
b0 /
b100 1
1#
#100000
0#
#105000
b1 0
b0 "
b0 .
b10 !
b10 /
b0 1
1#
#110000
0#
#115000
b10 0
b1 !
b1 /
b1 1
1#
#120000
0#
#125000
b11 0
b0 !
b0 /
b10 1
1#
#130000
0#
#135000
b100 0
b10 "
b10 .
b0 !
b0 /
b11 1
1#
#140000
0#
#145000
b0 0
b1 "
b1 .
b0 !
b0 /
b100 1
1#
#150000
0#
#155000
b1 0
b0 "
b0 .
b10 !
b10 /
b0 1
1#
#160000
0#
#162000
b0 0
0%
#165000
1#
#170000
0#
#175000
1#
#180000
0#
#185000
1#
#190000
0#
#195000
1#
#200000
0#
#205000
1#
#210000
0#
#215000
1#
#220000
0#
#225000
1#
#230000
0#
#235000
1#
#240000
0#
#245000
1#
#250000
0#
#255000
1#
#260000
0#
#262000
b1 0
1%
#265000
b10 0
b1 !
b1 /
b1 1
1#
#270000
0#
#275000
b11 0
b0 !
b0 /
b10 1
1#
#280000
0#
#285000
b100 0
b10 "
b10 .
b0 !
b0 /
b11 1
1#
#290000
0#
#295000
b0 0
b1 "
b1 .
b0 !
b0 /
b100 1
1#
#300000
0#
#305000
b1 0
b0 "
b0 .
b10 !
b10 /
b0 1
1#
#310000
0#
#315000
b10 0
b1 !
b1 /
b1 1
1#
#320000
0#
#325000
b11 0
b0 !
b0 /
b10 1
1#
#330000
0#
#335000
b100 0
b10 "
b10 .
b0 !
b0 /
b11 1
1#
