4-bit_ripple_carry_counter/RCC.v
module ripple_carry_counter (q, clk, rst);
    output [3:0] q;
    input clk;
    input rst;

    T_FF tff0 (q[0], clk, rst);
    T_FF tff1 (q[1], q[0], rst);
    T_FF tff2 (q[2], q[1], rst);
    T_FF tff3 (q[3], q[2], rst);

endmodule

module T_FF (q, clk ,rst);
    output q;
    input clk;
    input rst;
    wire d;

    D_FF dff0 (q, d, clk, rst);

    not n1(d, q);

endmodule

module D_FF (q, d, clk, rst);
    output q;
    input d;
    input clk;
    input rst;
    reg q;

    always @(posedge rst or negedge clk) begin
        if (rst)
            q = 1'b0;
        else
            q = d;
    end
endmodule

4-bit_ripple_carry_counter/tb_RCC.v
module stimulus;

reg clk;
reg rst;
wire [3:0] q;

ripple_carry_counter r1 (q, clk, rst);

initial begin
    clk = 1'b0;
end

always begin
    #5 clk = ~clk;
end

initial
begin
    rst = 1'b1;
    #15 rst = 1'b0;
    #180 rst = 1'b1;
    #10 rst = 1'b0;
    #20 $finish;
end

initial begin
    $monitor ($time, " Output q = %d", q);
    $dumpfile("tb_RCC.vcd");
    $dumpvars(0, stimulus);
end

endmodule

4-bit_ripple_carry_counter/tb_RCC.vcd
$date
	Sun Apr 13 15:49:31 2025
$end
$version
	Icarus Verilog
$end
$timescale
	1s
$end
$scope module stimulus $end
$var wire 4 ! q [3:0] $end
$var reg 1 " clk $end
$var reg 1 # rst $end
$scope module r1 $end
$var wire 1 " clk $end
$var wire 1 # rst $end
$var wire 4 $ q [3:0] $end
$scope module tff0 $end
$var wire 1 " clk $end
$var wire 1 % d $end
$var wire 1 # rst $end
$var wire 1 & q $end
$scope module dff0 $end
$var wire 1 " clk $end
$var wire 1 % d $end
$var wire 1 # rst $end
$var reg 1 & q $end
$upscope $end
$upscope $end
$scope module tff1 $end
$var wire 1 ' clk $end
$var wire 1 ( d $end
$var wire 1 # rst $end
$var wire 1 ) q $end
$scope module dff0 $end
$var wire 1 ' clk $end
$var wire 1 ( d $end
$var wire 1 # rst $end
$var reg 1 ) q $end
$upscope $end
$upscope $end
$scope module tff2 $end
$var wire 1 * clk $end
$var wire 1 + d $end
$var wire 1 # rst $end
$var wire 1 , q $end
$scope module dff0 $end
$var wire 1 * clk $end
$var wire 1 + d $end
$var wire 1 # rst $end
$var reg 1 , q $end
$upscope $end
$upscope $end
$scope module tff3 $end
$var wire 1 - clk $end
$var wire 1 . d $end
$var wire 1 # rst $end
$var wire 1 / q $end
$scope module dff0 $end
$var wire 1 - clk $end
$var wire 1 . d $end
$var wire 1 # rst $end
$var reg 1 / q $end
$upscope $end
$upscope $end
$upscope $end
$upscope $end
$enddefinitions $end
$comment Show the parameter values. $end
$dumpall
$end
#0
$dumpvars
0/
1.
0-
0,
1+
0*
0)
1(
0'
0&
1%
b0 $
1#
0"
b0 !
$end
#5
1"
#10
0"
#15
1"
0#
#20
0%
1'
b1 !
b1 $
1&
0"
#25
1"
#30
0(
1*
1)
1%
0'
b10 !
b10 $
0&
0"
#35
1"
#40
0%
1'
b11 !
b11 $
1&
0"
#45
1"
#50
0+
1-
1,
1(
0*
0)
1%
0'
b100 !
b100 $
0&
0"
#55
1"
#60
0%
1'
b101 !
b101 $
1&
0"
#65
1"
#70
0(
1*
1)
1%
0'
b110 !
b110 $
0&
0"
#75
1"
#80
0%
1'
b111 !
b111 $
1&
0"
#85
1"
#90
0.
1/
1+
0-
0,
1(
0*
0)
1%
0'
b1000 !
b1000 $
0&
0"
#95
1"
#100
0%
1'
b1001 !
b1001 $
1&
0"
#105
1"
#110
0(
1*
1)
1%
0'
b1010 !
b1010 $
0&
0"
#115
1"
#120
0%
1'
b1011 !
b1011 $
1&
0"
#125
1"
#130
0+
1-
1,
1(
0*
0)
1%
0'
b1100 !
b1100 $
0&
0"
#135
1"
#140
0%
1'
b1101 !
b1101 $
1&
0"
#145
1"
#150
0(
1*
1)
1%
0'
b1110 !
b1110 $
0&
0"
#155
1"
#160
0%
1'
b1111 !
b1111 $
1&
0"
#165
1"
#170
1.
0/
1+
0-
0,
1(
0*
0)
1%
0'
b0 !
b0 $
0&
0"
#175
1"
#180
0%
1'
b1 !
b1 $
1&
0"
#185
1"
#190
0(
1*
1)
1%
0'
b10 !
b10 $
0&
0"
#195
1(
0*
b0 !
b0 $
0)
1"
1#
#200
0"
#205
1"
0#
#210
0%
1'
b1 !
b1 $
1&
0"
#215
1"
#220
0(
1*
1)
1%
0'
b10 !
b10 $
0&
0"
