blocking_vs_nonblocking/nonblocking.v
module nonblocking_ff(input clk, input d, output reg q);
    reg temp;

    always @(posedge clk) begin
        temp <= d;
        q <= temp;  // temp 與 q 都是同步更新
    end
endmodule

blocking_vs_nonblocking/blocking.v
module blocking_ff(input clk, input d, output reg q);
    reg temp;

    always @(posedge clk) begin
        temp = d;
        q = temp;  // 先更新 temp，再給 q
    end
endmodule

blocking_vs_nonblocking/tb_assignment.v
`timescale 1ns/1ns

module tb;

    reg clk, d;
    wire q_blocking, q_nonblocking;

    // 建立兩種模組
    blocking_ff     u1 (.clk(clk), .d(d), .q(q_blocking));
    nonblocking_ff  u2 (.clk(clk), .d(d), .q(q_nonblocking));

    // 時脈產生器
    initial clk = 0;
    always #5 clk = ~clk;  // 10ns 週期

    // 測試刺激
    initial begin
        d = 0;
        #12 d = 1;
        #10 d = 0;
        #10 d = 1;
        #10 $finish;
    end

    // 波形與監控
    initial begin
        $dumpfile("blocking_vs_nonblocking.vcd");
        $dumpvars(0, tb);
        $monitor("Time=%0t | d=%b | blocking=%b | nonblocking=%b", 
                 $time, d, q_blocking, q_nonblocking);
    end

endmodule

blocking_vs_nonblocking/blocking_vs_nonblocking.vcd
$date
	Mon Apr 14 19:04:19 2025
$end
$version
	Icarus Verilog
$end
$timescale
	1ns
$end
$scope module tb $end
$var wire 1 ! q_nonblocking $end
$var wire 1 " q_blocking $end
$var reg 1 # clk $end
$var reg 1 $ d $end
$scope module u1 $end
$var wire 1 # clk $end
$var wire 1 $ d $end
$var reg 1 " q $end
$var reg 1 % temp $end
$upscope $end
$scope module u2 $end
$var wire 1 # clk $end
$var wire 1 $ d $end
$var reg 1 ! q $end
$var reg 1 & temp $end
$upscope $end
$upscope $end
$enddefinitions $end
$comment Show the parameter values. $end
$dumpall
$end
#0
$dumpvars
x&
x%
0$
0#
x"
x!
$end
#5
0&
0"
0%
1#
#10
0#
#12
1$
#15
0!
1&
1"
1%
1#
#20
0#
#22
0$
#25
1!
0&
0"
0%
1#
#30
0#
#32
1$
#35
0!
1&
1"
1%
1#
